bidshandler/__init__.py
bidshandler/bidserrors.py
bidshandler/bidstree.py
bidshandler/constants.py
bidshandler/project.py
bidshandler/querylist.py
bidshandler/querymixin.py
bidshandler/scan.py
bidshandler/session.py
bidshandler/subject.py
bidshandler/utils.py
BIDSHandler-0.2.1.dist-info/LICENSE
BIDSHandler-0.2.1.dist-info/METADATA
BIDSHandler-0.2.1.dist-info/WHEEL
BIDSHandler-0.2.1.dist-info/top_level.txt
BIDSHandler-0.2.1.dist-info/RECORD
