Metadata-Version: 2.1
Name: BIDSHandler
Version: 0.2.1
Summary: Simple way to manage and manipulate BIDS compatible data
Home-page: UNKNOWN
Author: Matt Sanderson
Author-email: matt.sanderson@mq.edu.au
License: MIT
Download-URL: https://github.com/Macquarie-MEG-Research/BIDSHandler
Project-URL: Documentation, https://macquarie-meg-research.github.io/BIDSHandler/
Platform: UNKNOWN
Classifier: Programming Language :: Python :: 3
Classifier: License :: OSI Approved :: MIT License
Classifier: Operating System :: OS Independent
